doommoses/__init__.py
doommoses/chinese.py
doommoses/cli.py
doommoses/corpus.py
doommoses/normalize.py
doommoses/sent_tokenize.py
doommoses/subwords.py
doommoses/tokenize.py
doommoses/truecase.py
doommoses/util.py
doommoses/data/nonbreaking_prefixes/nonbreaking_prefix.ca
doommoses/data/nonbreaking_prefixes/nonbreaking_prefix.cs
doommoses/data/nonbreaking_prefixes/nonbreaking_prefix.de
doommoses/data/nonbreaking_prefixes/nonbreaking_prefix.el
doommoses/data/nonbreaking_prefixes/nonbreaking_prefix.en
doommoses/data/nonbreaking_prefixes/nonbreaking_prefix.es
doommoses/data/nonbreaking_prefixes/nonbreaking_prefix.fi
doommoses/data/nonbreaking_prefixes/nonbreaking_prefix.fr
doommoses/data/nonbreaking_prefixes/nonbreaking_prefix.ga
doommoses/data/nonbreaking_prefixes/nonbreaking_prefix.hu
doommoses/data/nonbreaking_prefixes/nonbreaking_prefix.is
doommoses/data/nonbreaking_prefixes/nonbreaking_prefix.it
doommoses/data/nonbreaking_prefixes/nonbreaking_prefix.lt
doommoses/data/nonbreaking_prefixes/nonbreaking_prefix.lv
doommoses/data/nonbreaking_prefixes/nonbreaking_prefix.nl
doommoses/data/nonbreaking_prefixes/nonbreaking_prefix.pl
doommoses/data/nonbreaking_prefixes/nonbreaking_prefix.pt
doommoses/data/nonbreaking_prefixes/nonbreaking_prefix.ro
doommoses/data/nonbreaking_prefixes/nonbreaking_prefix.ru
doommoses/data/nonbreaking_prefixes/nonbreaking_prefix.sk
doommoses/data/nonbreaking_prefixes/nonbreaking_prefix.sl
doommoses/data/nonbreaking_prefixes/nonbreaking_prefix.sv
doommoses/data/nonbreaking_prefixes/nonbreaking_prefix.ta
doommoses/data/nonbreaking_prefixes/nonbreaking_prefix.yue
doommoses/data/nonbreaking_prefixes/nonbreaking_prefix.zh
doommoses/data/perluniprops/CJK.txt
doommoses/data/perluniprops/CJKSymbols.txt
doommoses/data/perluniprops/Close_Punctuation.txt
doommoses/data/perluniprops/Currency_Symbol.txt
doommoses/data/perluniprops/Han.txt
doommoses/data/perluniprops/Hangul.txt
doommoses/data/perluniprops/Hangul_Syllables.txt
doommoses-0.0.43.dist-info/LICENSE
doommoses-0.0.43.dist-info/METADATA
doommoses-0.0.43.dist-info/WHEEL
doommoses-0.0.43.dist-info/entry_points.txt
doommoses-0.0.43.dist-info/top_level.txt
doommoses-0.0.43.dist-info/RECORD
